Metadata-Version: 1.1
Name: dm.zopepatches.logging
Version: 1.0
Summary: Use Zope exception format for logging
Home-page: https://pypi.org/project/dm.zopepatches.logging
Author: Dieter Maurer
Author-email: dieter@handshake.de
License: BSD
Keywords: logging Zope exception
Platform: UNKNOWN
Classifier: Development Status :: 5 - Production/Stable
Classifier: Intended Audience :: Developers
Classifier: License :: OSI Approved :: Zope Public License
Classifier: Framework :: Zope
Classifier: Operating System :: OS Independent
Classifier: Programming Language :: Python
Classifier: Topic :: Utilities
